azure/storage/common/__init__.py
azure/storage/common/_auth.py
azure/storage/common/_common_conversion.py
azure/storage/common/_connection.py
azure/storage/common/_constants.py
azure/storage/common/_deserialization.py
azure/storage/common/_encryption.py
azure/storage/common/_error.py
azure/storage/common/_serialization.py
azure/storage/common/cloudstorageaccount.py
azure/storage/common/models.py
azure/storage/common/retry.py
azure/storage/common/sharedaccesssignature.py
azure/storage/common/storageclient.py
azure/storage/common/tokencredential.py
azure/storage/common/_http/__init__.py
azure/storage/common/_http/httpclient.py
azure_storage_common-2.0.0.dist-info/LICENSE.txt
azure_storage_common-2.0.0.dist-info/METADATA
azure_storage_common-2.0.0.dist-info/WHEEL
azure_storage_common-2.0.0.dist-info/top_level.txt
azure_storage_common-2.0.0.dist-info/RECORD
